dyn_struct/__init__.py
dyn_struct/admin.py
dyn_struct/datatools.py
dyn_struct/exceptions.py
dyn_struct/factories.py
dyn_struct/forms.py
dyn_struct/db/__init__.py
dyn_struct/db/fields.py
dyn_struct/db/models.py
dyn_struct/db/validators.py
dyn_struct/management/__init__.py
dyn_struct/management/commands/__init__.py
dyn_struct/management/commands/dump_dynamic_structure.py
dyn_struct/management/commands/dump_one_dynamic_structure.py
dyn_struct/management/commands/load_dynamic_structure.py
dyn_struct/management/commands/load_one_dynamic_structure.py
dyn_struct/migrations/0001_initial.py
dyn_struct/migrations/0002_auto_20160831_2238.py
dyn_struct/migrations/0003_auto_20160906_1255.py
dyn_struct/migrations/0004_auto_20160912_1752.py
dyn_struct/migrations/0005_auto_20160913_1041.py
dyn_struct/migrations/0006_auto_20200117_2316.py
dyn_struct/migrations/__init__.py
dyn_struct/templates/dyn_struct/render_struct.html
dyn_struct/templates/dyn_struct/render_struct_field_bootstrap2.html
dyn_struct/templates/dyn_struct/render_struct_field_bootstrap3.html
dyn_struct/templatetags/__init__.py
dyn_struct/templatetags/dyn_struct.py
dyn_struct/tests/__init__.py
dyn_struct/tests/test_datatools.py
dyn_struct/tests/test_forms.py
dyn_struct/tests/db/__init__.py
dyn_struct/tests/db/test_fields.py
dyn_struct/tests/db/test_validators.py
dyn_struct/tests/db/models/__init__.py
dyn_struct/tests/db/models/test_dynamic_structure.py
dyn_struct/tests/db/models/test_dynamic_structure_field.py
django_dynamic_structure-0.0.34.dist-info/METADATA
django_dynamic_structure-0.0.34.dist-info/WHEEL
django_dynamic_structure-0.0.34.dist-info/top_level.txt
django_dynamic_structure-0.0.34.dist-info/RECORD
